README.md
setup.py
up_or_down/__init__.py
up_or_down/up_or_down.py
webwatchdog.egg-info/PKG-INFO
webwatchdog.egg-info/SOURCES.txt
webwatchdog.egg-info/dependency_links.txt
webwatchdog.egg-info/requires.txt
webwatchdog.egg-info/top_level.txt