Metadata-Version: 2.1
Name: webwatchdog
Version: 1.0.2
Summary: A Python library to check if a website is up or down.
Author: itsknk
